odoo/addons/shopinvader_api_delivery_carrier/README.rst
odoo/addons/shopinvader_api_delivery_carrier/__init__.py
odoo/addons/shopinvader_api_delivery_carrier/__manifest__.py
odoo/addons/shopinvader_api_delivery_carrier/i18n/shopinvader_api_delivery_carrier.pot
odoo/addons/shopinvader_api_delivery_carrier/i18n/shopinvader_delivery_carrier.pot
odoo/addons/shopinvader_api_delivery_carrier/readme/CONTRIBUTORS.rst
odoo/addons/shopinvader_api_delivery_carrier/readme/DESCRIPTION.rst
odoo/addons/shopinvader_api_delivery_carrier/readme/USAGE.rst
odoo/addons/shopinvader_api_delivery_carrier/routers/__init__.py
odoo/addons/shopinvader_api_delivery_carrier/routers/cart.py
odoo/addons/shopinvader_api_delivery_carrier/routers/delivery.py
odoo/addons/shopinvader_api_delivery_carrier/routers/delivery_carrier.py
odoo/addons/shopinvader_api_delivery_carrier/schemas/__init__.py
odoo/addons/shopinvader_api_delivery_carrier/schemas/amount.py
odoo/addons/shopinvader_api_delivery_carrier/schemas/delivery.py
odoo/addons/shopinvader_api_delivery_carrier/schemas/delivery_carrier.py
odoo/addons/shopinvader_api_delivery_carrier/schemas/picking.py
odoo/addons/shopinvader_api_delivery_carrier/schemas/sale_line.py
odoo/addons/shopinvader_api_delivery_carrier/security/acl_account_tax.xml
odoo/addons/shopinvader_api_delivery_carrier/security/acl_choose_delivery_carrier.xml
odoo/addons/shopinvader_api_delivery_carrier/security/acl_delivery_carrier.xml
odoo/addons/shopinvader_api_delivery_carrier/security/acl_product_category.xml
odoo/addons/shopinvader_api_delivery_carrier/security/acl_product_pricelist.xml
odoo/addons/shopinvader_api_delivery_carrier/security/acl_product_pricelist_item.xml
odoo/addons/shopinvader_api_delivery_carrier/security/acl_product_product.xml
odoo/addons/shopinvader_api_delivery_carrier/security/acl_product_template.xml
odoo/addons/shopinvader_api_delivery_carrier/security/acl_sale_order.xml
odoo/addons/shopinvader_api_delivery_carrier/security/acl_sale_order_line.xml
odoo_addon_shopinvader_api_delivery_carrier-16.0.1.1.1.dist-info/METADATA
odoo_addon_shopinvader_api_delivery_carrier-16.0.1.1.1.dist-info/WHEEL
odoo_addon_shopinvader_api_delivery_carrier-16.0.1.1.1.dist-info/top_level.txt
odoo_addon_shopinvader_api_delivery_carrier-16.0.1.1.1.dist-info/RECORD
