Metadata-Version: 2.1
Name: odoo-addon-shopinvader_api_delivery_carrier
Version: 16.0.1.1.1
Summary: Carrier integration for Shopinvader
Home-page: https://github.com/shopinvader/odoo-shopinvader-carrier
Author: Akretion, Acsone SA/NV,Shopinvader
License: AGPL-3
Classifier: Programming Language :: Python
Classifier: Framework :: Odoo
Classifier: Framework :: Odoo :: 16.0
Classifier: License :: OSI Approved :: GNU Affero General Public License v3
Classifier: Development Status :: 3 - Alpha
Requires-Python: >=3.10
Requires-Dist: extendable-pydantic>=1.2.0
Requires-Dist: fastapi
Requires-Dist: odoo-addon-delivery-carrier-info<16.1dev,>=16.0dev
Requires-Dist: odoo-addon-extendable<16.1dev,>=16.0dev
Requires-Dist: odoo-addon-extendable-fastapi<16.1dev,>=16.0dev
Requires-Dist: odoo-addon-fastapi<16.1dev,>=16.0dev
Requires-Dist: odoo-addon-pydantic<16.1dev,>=16.0dev
Requires-Dist: odoo-addon-queue-job<16.1dev,>=16.0dev
Requires-Dist: odoo-addon-sale-discount-display-amount<16.1dev,>=16.0dev
Requires-Dist: odoo-addon-sale-shipping-info-helper<16.1dev,>=16.0dev
Requires-Dist: odoo-addon-shopinvader-api-cart<16.1dev,>=16.0dev
Requires-Dist: odoo-addon-shopinvader-api-security-sale<16.1dev,>=16.0dev
Requires-Dist: odoo-addon-shopinvader-delivery-carrier<16.1dev,>=16.0dev
Requires-Dist: odoo-addon-shopinvader-filtered-model<16.1dev,>=16.0dev
Requires-Dist: odoo-addon-shopinvader-sale-cart<16.1dev,>=16.0dev
Requires-Dist: odoo-addon-shopinvader-schema-sale<16.1dev,>=16.0dev
Requires-Dist: odoo<16.1dev,>=16.0a
Requires-Dist: pydantic>=2.0.0
